social_auth_kerberos/__init__.py
social_auth_kerberos/backend.py
social_auth_kerberos/pipeline.py
social_auth_kerberos-0.3.0.dist-info/LICENSE
social_auth_kerberos-0.3.0.dist-info/METADATA
social_auth_kerberos-0.3.0.dist-info/WHEEL
social_auth_kerberos-0.3.0.dist-info/top_level.txt
social_auth_kerberos-0.3.0.dist-info/RECORD
