Metadata-Version: 2.1
Name: social-auth-kerberos
Version: 0.3.0
Summary: Kerberos authentication backend for Python Social Auth
Home-page: https://github.com/kiwitcms/python-social-auth-kerberos/
Author: Kiwi TCMS
Author-email: info@kiwitcms.org
License: GPLv2
Keywords: social auth,kerberos
Classifier: Development Status :: 4 - Beta
Classifier: Topic :: Internet
Classifier: Environment :: Web Environment
Classifier: Intended Audience :: Developers
Classifier: License :: OSI Approved :: GNU General Public License v2 (GPLv2)
Classifier: Programming Language :: Python :: 3
Classifier: Programming Language :: Python :: 3.8
Classifier: Programming Language :: Python :: 3.9
Classifier: Programming Language :: Python :: 3.11
License-File: LICENSE
Requires-Dist: social-auth-core
Requires-Dist: gssapi
